manytime/__init__.py
manytime/analysis.py
manytime/interactive.py
manytime/keys.py
manytime/models.py
mtp-1.1.0.data/scripts/cli.py
mtp-1.1.0.dist-info/LICENSE
mtp-1.1.0.dist-info/METADATA
mtp-1.1.0.dist-info/WHEEL
mtp-1.1.0.dist-info/entry_points.txt
mtp-1.1.0.dist-info/top_level.txt
mtp-1.1.0.dist-info/RECORD
